datalab_processing/__init__.py
datalab_processing-0.0.1.dev0.dist-info/licenses/LICENSE
datalab_processing-0.0.1.dev0.dist-info/METADATA
datalab_processing-0.0.1.dev0.dist-info/WHEEL
datalab_processing-0.0.1.dev0.dist-info/top_level.txt
datalab_processing-0.0.1.dev0.dist-info/RECORD
